.coveragerc
.editorconfig
CHANGES.rst
CONTRIBUTORS.rst
MANIFEST.in
README.rst
buildout.cfg
requirements.txt
setup.py
docs/HISTORY.txt
docs/INSTALL.txt
docs/LICENSE.GPL
docs/LICENSE.txt
docs/Makefile
docs/conf.py
docs/index.rst
docs/make.bat
docs/resources/add_token.png
docs/resources/manage_tokens.png
redomino/__init__.py
redomino.tokenrole.egg-info/PKG-INFO
redomino.tokenrole.egg-info/SOURCES.txt
redomino.tokenrole.egg-info/dependency_links.txt
redomino.tokenrole.egg-info/entry_points.txt
redomino.tokenrole.egg-info/namespace_packages.txt
redomino.tokenrole.egg-info/not-zip-safe
redomino.tokenrole.egg-info/requires.txt
redomino.tokenrole.egg-info/top_level.txt
redomino/tokenrole/LICENSE.txt
redomino/tokenrole/__init__.py
redomino/tokenrole/config.py
redomino/tokenrole/configure.zcml
redomino/tokenrole/i18n.sh
redomino/tokenrole/interfaces.py
redomino/tokenrole/permissions.zcml
redomino/tokenrole/setuphandlers.py
redomino/tokenrole/testing.py
redomino/tokenrole/tokenroleprovider.py
redomino/tokenrole/validators.py
redomino/tokenrole/vocabularies.py
redomino/tokenrole/vocabularies.zcml
redomino/tokenrole/browser/__init__.py
redomino/tokenrole/browser/actions.py
redomino/tokenrole/browser/configure.zcml
redomino/tokenrole/browser/interfaces.py
redomino/tokenrole/browser/send_token.py
redomino/tokenrole/browser/token_manage.pt
redomino/tokenrole/browser/token_manage.py
redomino/tokenrole/browser/validators.py
redomino/tokenrole/browser/resources/delete.png
redomino/tokenrole/browser/resources/email.png
redomino/tokenrole/browser/resources/modify.png
redomino/tokenrole/browser/resources/tokenrole.css
redomino/tokenrole/locales/plone.pot
redomino/tokenrole/locales/redomino.tokenrole.pot
redomino/tokenrole/locales/de/LC_MESSAGES/plone.po
redomino/tokenrole/locales/de/LC_MESSAGES/redomino.tokenrole.po
redomino/tokenrole/locales/en/LC_MESSAGES/plone.po
redomino/tokenrole/locales/en/LC_MESSAGES/redomino.tokenrole.po
redomino/tokenrole/locales/it/LC_MESSAGES/plone.po
redomino/tokenrole/locales/it/LC_MESSAGES/redomino.tokenrole.po
redomino/tokenrole/plugins/__init__.py
redomino/tokenrole/plugins/tokenrole.py
redomino/tokenrole/plugins/www/tokenRoleAdd.zpt
redomino/tokenrole/profiles/default/actions.xml
redomino/tokenrole/profiles/default/cssregistry.xml
redomino/tokenrole/profiles/default/import_steps.xml
