Metadata-Version: 2.1
Name: redomino.tokenrole
Version: 1.1
Summary: This product allows you to share roles about a specific Plone content to an unregistered user through a link.
Home-page: https://pypi.python.org/pypi/redomino.tokenrole
Author: Redomino S.r.l.
Author-email: info@redomino.com
License: GPL
Keywords: Python Plone
Platform: UNKNOWN
Classifier: Environment :: Web Environment
Classifier: Framework :: Plone
Classifier: Framework :: Plone :: 5.0
Classifier: Framework :: Plone :: 5.1
Classifier: Programming Language :: Python
Classifier: Programming Language :: Python :: 2.7
Classifier: Operating System :: OS Independent
Classifier: License :: OSI Approved :: GNU General Public License v2 (GPLv2)
Provides-Extra: test
